odoo10_addon_l10n_fr_naf_ape-10.0.1.0.0.99.dev8-py2.7-nspkg.pth
odoo/addons/l10n_fr_naf_ape/README.rst
odoo/addons/l10n_fr_naf_ape/__init__.py
odoo/addons/l10n_fr_naf_ape/__manifest__.py
odoo/addons/l10n_fr_naf_ape/data/res.partner.category.csv
odoo/addons/l10n_fr_naf_ape/i18n/bg.po
odoo/addons/l10n_fr_naf_ape/i18n/da.po
odoo/addons/l10n_fr_naf_ape/i18n/de.po
odoo/addons/l10n_fr_naf_ape/i18n/el_GR.po
odoo/addons/l10n_fr_naf_ape/i18n/es.po
odoo/addons/l10n_fr_naf_ape/i18n/es_MX.po
odoo/addons/l10n_fr_naf_ape/i18n/fi.po
odoo/addons/l10n_fr_naf_ape/i18n/fr.po
odoo/addons/l10n_fr_naf_ape/i18n/fr_CH.po
odoo/addons/l10n_fr_naf_ape/i18n/hr.po
odoo/addons/l10n_fr_naf_ape/i18n/it.po
odoo/addons/l10n_fr_naf_ape/i18n/l10n_fr_naf_ape.pot
odoo/addons/l10n_fr_naf_ape/i18n/nb_NO.po
odoo/addons/l10n_fr_naf_ape/i18n/nl.po
odoo/addons/l10n_fr_naf_ape/i18n/pt.po
odoo/addons/l10n_fr_naf_ape/i18n/pt_BR.po
odoo/addons/l10n_fr_naf_ape/i18n/sl.po
odoo/addons/l10n_fr_naf_ape/models/__init__.py
odoo/addons/l10n_fr_naf_ape/models/partner.py
odoo/addons/l10n_fr_naf_ape/static/description/icon.png
odoo/addons/l10n_fr_naf_ape/views/partner.xml
odoo10_addon_l10n_fr_naf_ape-10.0.1.0.0.99.dev8.dist-info/METADATA
odoo10_addon_l10n_fr_naf_ape-10.0.1.0.0.99.dev8.dist-info/RECORD
odoo10_addon_l10n_fr_naf_ape-10.0.1.0.0.99.dev8.dist-info/WHEEL
odoo10_addon_l10n_fr_naf_ape-10.0.1.0.0.99.dev8.dist-info/namespace_packages.txt
odoo10_addon_l10n_fr_naf_ape-10.0.1.0.0.99.dev8.dist-info/top_level.txt
